AIML_Bot_API-0.0.dist-info/DESCRIPTION.rst
AIML_Bot_API-0.0.dist-info/METADATA
AIML_Bot_API-0.0.dist-info/RECORD
AIML_Bot_API-0.0.dist-info/WHEEL
AIML_Bot_API-0.0.dist-info/metadata.json
AIML_Bot_API-0.0.dist-info/top_level.txt
aiml_bot_api/__init__.py
aiml_bot_api/data.py
aiml_bot_api/endpoints.py
aiml_bot_api/graphql.py
