Metadata-Version: 2.0
Name: AIML-Bot-API
Version: 0.0
Summary: GraphQL API to AIML Bot
Home-page: https://github.com/hosford42/aiml_bot_api
Author: Aaron Hosford
Author-email: aaron.hosford@ericsson.com
License: MIT
Platform: any
Classifier: Development Status :: 3 - Alpha
Classifier: Environment :: Web Environment
Classifier: Intended Audience :: Developers
Classifier: Programming Language :: Python :: 3
Classifier: Operating System :: OS Independent
Classifier: Topic :: Communications :: Chat
Classifier: Topic :: Scientific/Engineering :: Artificial Intelligence
Requires-Dist: aiml-bot
Requires-Dist: flask
Requires-Dist: flask-graphql
Requires-Dist: graphene
